pyeventbus/aws/__init__.py
pyeventbus/aws/sns_event_bus.py
pyeventbus/base/__init__.py
pyeventbus/base/domain_event.py
pyeventbus/base/eventbus.py
pyeventbus/base/eventbus_exceptions.py
python3_eventbus-0.1.6.dist-info/LICENSE
python3_eventbus-0.1.6.dist-info/METADATA
python3_eventbus-0.1.6.dist-info/WHEEL
python3_eventbus-0.1.6.dist-info/RECORD
