Metadata-Version: 2.1
Name: python3-eventbus
Version: 0.1.6
Summary: Event bus implementation for Python
License: MIT
Keywords: eventbus,event,bus,python
Author: Álvaro Torres Cogollo
Author-email: atorrescogollo@gmail.com
Requires-Python: >=3.12,<4.0
Classifier: License :: OSI Approved :: MIT License
Classifier: Programming Language :: Python :: 3
Classifier: Programming Language :: Python :: 3.12
Classifier: Topic :: Software Development :: Libraries :: Python Modules
Classifier: Topic :: Utilities
Classifier: Typing :: Typed
Requires-Dist: boto3[sns] (>=1.34.7,<2.0.0)
Project-URL: Issues, https://github.com/atorrescogollo/pyeventbus/issues
